snmpack/__init__.py
snmpack/exceptions.py
snmpack/objects.py
snmpack/request.py
snmpack/response.py
snmpack/serializer.py
snmpack/tests/test_request.py
snmpack-1.0.0.dist-info/LICENSE
snmpack-1.0.0.dist-info/METADATA
snmpack-1.0.0.dist-info/WHEEL
snmpack-1.0.0.dist-info/top_level.txt
snmpack-1.0.0.dist-info/RECORD
